wayanjupyters3/__init__.py
wayanjupyters3/jupyters3.py
wayanjupyters3-0.0.4.dist-info/LICENSE
wayanjupyters3-0.0.4.dist-info/METADATA
wayanjupyters3-0.0.4.dist-info/WHEEL
wayanjupyters3-0.0.4.dist-info/top_level.txt
wayanjupyters3-0.0.4.dist-info/RECORD
