Metadata-Version: 2.1
Name: wayanjupyters3
Version: 0.0.4
Summary: Jupyter Notebook Contents Manager for AWS S3
Home-page: https://github.com/wayanedi/jupyters3
Author: Department for International Trade - WebOps
Author-email: webops@digital.trade.gov.uk
License: UNKNOWN
Platform: UNKNOWN
Classifier: Programming Language :: Python :: 3
Classifier: License :: OSI Approved :: MIT License
Classifier: Operating System :: OS Independent
